MANIFEST.in
run_cassava.py
setup.py
cassava/__init__.py
cassava/automater.py
cassava/bulk_analyze.py
cassava/config.py
cassava/dbcache.py
cassava/dig.py
cassava/extract_iocs.py
cassava/opendns.py
cassava/search_splunk.py
cassava/tapioca.py
cassava/utils.py
cassava/virustotal.py
cassava/whois.py
cassava.egg-info/PKG-INFO
cassava.egg-info/SOURCES.txt
cassava.egg-info/dependency_links.txt
cassava.egg-info/requires.txt
cassava.egg-info/top_level.txt
cassava/Automater/Automater.py
cassava/Automater/LICENSE
cassava/Automater/README.md
cassava/Automater/__init__.py
cassava/Automater/__init__.pyc
cassava/Automater/inputs.py
cassava/Automater/inputs.pyc
cassava/Automater/outputs.py
cassava/Automater/outputs.pyc
cassava/Automater/siteinfo.py
cassava/Automater/siteinfo.pyc
cassava/Automater/sites.xml
cassava/Automater/tekdefense.xml
cassava/Automater/utilities.py
cassava/Automater/utilities.pyc
cassava/Automater/docs/Automater.html
cassava/Automater/docs/inputs.html
cassava/Automater/docs/outputs.html
cassava/Automater/docs/siteinfo.html
cassava/Automater/docs/utilities.html
cassava/investigate/LICENSE
cassava/investigate/__init__.py
cassava/investigate/__init__.pyc
cassava/investigate/investigate.py
cassava/investigate/investigate.pyc
cassava_scrypture/__init__.py
cassava_scrypture/ActiveLookups/__init__.py
cassava_scrypture/ActiveLookups/dig.py
cassava_scrypture/ActiveLookups/whois.py
cassava_scrypture/Automater/__init__.py
cassava_scrypture/Automater/automater.py
cassava_scrypture/OpenDNS/__init__.py
cassava_scrypture/OpenDNS/categorization.py
cassava_scrypture/OpenDNS/cooccurrences.py
cassava_scrypture/OpenDNS/email_whois.py
cassava_scrypture/OpenDNS/investigate_everything.py
cassava_scrypture/OpenDNS/malicious_domains.py
cassava_scrypture/OpenDNS/odns_whois.py
cassava_scrypture/OpenDNS/related_domains.py
cassava_scrypture/OpenDNS/security_info.py
cassava_scrypture/Tapioca/__init__.py
cassava_scrypture/Tapioca/tapioca.py
cassava_scrypture/VirusTotal/__init__.py
cassava_scrypture/VirusTotal/virustotal_domain.py
cassava_scrypture/VirusTotal/virustotal_file.py
cassava_scrypture/VirusTotal/virustotal_ip.py