Metadata-Version: 1.1
Name: cassava
Version: 0.1.0
Summary: Library and web UI for analyzing IOCs with multiple APIs
Home-page: https://github.com/mosesschwartz/curl_to_requests
Author: Moses Schwartz, Bechtel CIRT
Author-email: moses.schwartz@gmail.com
License: MIT
Keywords: ioc security analysis
Platform: UNKNOWN
Classifier: Development Status :: 3 - Alpha
Classifier: Intended Audience :: Developers
Classifier: Topic :: Software Development
Classifier: Topic :: Utilities
Classifier: License :: OSI Approved :: MIT License
Classifier: Programming Language :: Python :: 2
Classifier: Programming Language :: Python :: 2.7
